CHANGELOG.md
LICENSE
MANIFEST.in
README.md
setup.cfg
setup.py
pip_services3_rpc/__init__.py
pip_services3_rpc.egg-info/PKG-INFO
pip_services3_rpc.egg-info/SOURCES.txt
pip_services3_rpc.egg-info/dependency_links.txt
pip_services3_rpc.egg-info/requires.txt
pip_services3_rpc.egg-info/top_level.txt
pip_services3_rpc.egg-info/zip-safe
pip_services3_rpc/auth/BasicAuthorizer.py
pip_services3_rpc/auth/OwnerAuthorizer.py
pip_services3_rpc/auth/RoleAuthorizer.py
pip_services3_rpc/auth/__init__.py
pip_services3_rpc/build/DefaultRpcFactory.py
pip_services3_rpc/build/__init__.py
pip_services3_rpc/clients/CommandableHttpClient.py
pip_services3_rpc/clients/DirectClient.py
pip_services3_rpc/clients/RestClient.py
pip_services3_rpc/clients/__init__.py
pip_services3_rpc/connect/HttpConnectionResolver.py
pip_services3_rpc/connect/__init__.py
pip_services3_rpc/services/AboutOperations.py
pip_services3_rpc/services/CommandableHttpService.py
pip_services3_rpc/services/CommandableSwaggerDocument.py
pip_services3_rpc/services/HeartBeatOperations.py
pip_services3_rpc/services/HeartbeatRestService.py
pip_services3_rpc/services/HttpEndpoint.py
pip_services3_rpc/services/HttpRequestDetector.py
pip_services3_rpc/services/HttpResponseSender.py
pip_services3_rpc/services/IRegisterable.py
pip_services3_rpc/services/ISwaggerService.py
pip_services3_rpc/services/InstrumentTiming.py
pip_services3_rpc/services/RestOperations.py
pip_services3_rpc/services/RestQueryParams.py
pip_services3_rpc/services/RestService.py
pip_services3_rpc/services/SSLCherryPyServer.py
pip_services3_rpc/services/StatusOperations.py
pip_services3_rpc/services/StatusRestService.py
pip_services3_rpc/services/__init__.py
pip_services3_rpc/test/TestCommandableHttpClient.py
pip_services3_rpc/test/TestRestClient.py
pip_services3_rpc/test/__init__.py
test/clients/DummyClientFixture.py
test/clients/DummyCommandableHttpClient.py
test/clients/DummyDirectClient.py
test/clients/DummyRestClient.py
test/clients/IDummyClient.py
test/clients/__init__.py
test/clients/test_DummyCommandableHttpClient.py
test/clients/test_DummyDirectClient.py
test/clients/test_DummyRestClient.py
test/connect/__init__.py
test/connect/test_HttpConnectionResolver.py
